{
	"id": "0706e744-4786-40f6-8aa2-b825ed8e9cf2",
	"name": "mobivia.localhost",
	"values": [
		{
			"key": "dapp-id",
			"value": "collaborate-dapp-movidia",
			"enabled": true
		},
		{
			"key": "dAppKeycloakUrl",
			"value": "http://movidia.localhost",
			"enabled": true
		},
		{
			"key": "dAppKeycloakFrontendClientId",
			"value": "frontend",
			"enabled": true
		},
		{
			"key": "dAppKeycloakRealm",
			"value": "collaborate-dapp",
			"enabled": true
		},
		{
			"key": "dAppKeycloakUsername",
			"value": "admin",
			"enabled": true
		},
		{
			"key": "dAppKeycloakPassword",
			"value": "admin",
			"enabled": true
		},
		{
			"key": "dAppToken",
			"value": "",
			"enabled": true
		},
		{
			"key": "dAppApiUrl",
			"value": "http://movidia.localhost",
			"enabled": true
		},
		{
			"key": "organizationId",
			"value": "movidia",
			"enabled": true
		},
		{
			"key": "smart-contract-address",
			"value": "KT1X2GBRQ7ADbJv9gHNKGKuGJKBgZGbcRd4U",
			"enabled": true
		},
		{
			"key": "tagApiUrl",
			"value": "http://tezos-api-gateway.movidia.localhost",
			"enabled": true
		},
		{
			"key": "tag-admin",
			"value": "admin",
			"enabled": true
		},
		{
			"key": "tag-admin-publicKeyHash",
			"value": "tz1QdgwqsVV7SmpFPrWjs9B5oBNcj2brzqfG",
			"enabled": true
		},
		{
			"key": "tag-mobivia-publicKeyHash",
			"value": "tz1QdgwqsVV7SmpFPrWjs9B5oBNcj2brzqfG",
			"enabled": true
		},
		{
			"key": "tag-psa-publicKeyHash",
			"value": "tz1NSuGfg7Tfy8WUxrqWjRSVtTtW8HCMUegV",
			"enabled": true
		},
		{
			"key": "tag-other-publicKeyHash",
			"value": "tz1NSuGfg7Tfy8WUxrqWjRSVtTtW8HCMUegV",
			"enabled": true
		},
		{
			"key": "keycloak-admin-token",
			"value": "",
			"enabled": true
		},
		{
			"key": "test-asset-owner-email",
			"value": "",
			"enabled": true
		},
		{
			"key": "test-asset-owner-username",
			"value": "",
			"enabled": true
		},
		{
			"key": "test-asset-owner-password",
			"value": "",
			"enabled": true
		},
		{
			"key": "test-asset-owner-id",
			"value": "",
			"enabled": true
		},
		{
			"key": "test-dsp-email",
			"value": "",
			"enabled": true
		},
		{
			"key": "test-dsp-username",
			"value": "",
			"enabled": true
		},
		{
			"key": "test-dsp-password",
			"value": "",
			"enabled": true
		},
		{
			"key": "test-dsp-id",
			"value": "",
			"enabled": true
		},
		{
			"key": "test-datasource-id",
			"value": "",
			"enabled": true
		},
		{
			"key": "test-asset-owner-token",
			"value": "",
			"enabled": true
		}
	],
	"_postman_variable_scope": "environment",
	"_postman_exported_at": "2021-08-25T08:58:43.590Z",
	"_postman_exported_using": "Postman/8.10.0"
}